[
    {
        "image": {
            "en": "1_en.jpg",
            "ar": "1_ar.jpg"
        },
        "p1": [
            {
                "text": {
                    "en": "In the heart of the Arab World, A transformation is taking place – one that will change the future of literacy forever.",
                    "ar": "في قلب العالم العربي، يجري تحول سيغير مستقبل محو الأمية إلى الأبد."
                },
                "audio": {
                    "en": "1_en.mp3",
                    "ar": "1_ar.mp3"
                }
            }
        ]
    },
    {
        "image": {
            "en": "2_en.jpg",
            "ar": "2_ar.jpg"
        },
        "p1": [
            {
                "text": {
                    "en": "Sami is discovering stories in a way he never has before...",
                    "ar": "سامي يكتشف القصص بطريقة لم يعهدها من قبل..."
                },
                "audio": {
                    "en": "2_en.mp3",
                    "ar": "2_ar.mp3"
                }
            }
        ],
        "p2": [
            {
                "text": {
                    "en": "Huh! Abu Zayd is too clever!",
                    "ar": "هاهاها! أبو زيد ذكي جدًا!"
                },
                "audio": {
                    "en": "21_en.mp3",
                    "ar": "21_ar.mp3"
                }
            }
        ]
    },
    {
        "image": {
            "en": "3_en.jpg",
            "ar": "3_ar.jpg"
        },
        "text": {
            "en": "With the power of engaging comic adaptations, Arabic is now accessible to young minds.",
            "ar": " بفضل قوة الاقتباسات المصورة المشوقة، أصبحت اللغة العربية في متناول عقول الشباب."
        },
        "audio": {
            "en": "3_en.mp3",
            "ar": "3_ar.mp3"
        }
    },
    {
        "image": {
            "en": "4_en.jpg",
            "ar": "4_ar.jpg"
        },
        "p1": [
            {
                "text": {
                    "en": "What are you watching, Sami?",
                    "ar": "ماذا تشاهد يا سامي؟"
                },
                "audio": {
                    "en": "4_en.mp3",
                    "ar": "4_ar.mp3"
                }
            }
        ],
        "p2": [
            {
                "text": {
                    "en": "I’m reading, Mama. Look how awesome this art is?",
                    "ar": "أنا أقرأ يا أمي. انظري كم هذا الفن رائع؟"
                },
                "audio": {
                    "en": "41_en.mp3",
                    "ar": "41_ar.mp3"
                }
            }
        ]
    }
]